odoo8_addon_ovh_telephony_connector-8.0.0.1.0.99.dev10-py2.7-nspkg.pth
odoo8_addon_ovh_telephony_connector-8.0.0.1.0.99.dev10.dist-info/METADATA
odoo8_addon_ovh_telephony_connector-8.0.0.1.0.99.dev10.dist-info/RECORD
odoo8_addon_ovh_telephony_connector-8.0.0.1.0.99.dev10.dist-info/WHEEL
odoo8_addon_ovh_telephony_connector-8.0.0.1.0.99.dev10.dist-info/namespace_packages.txt
odoo8_addon_ovh_telephony_connector-8.0.0.1.0.99.dev10.dist-info/top_level.txt
odoo_addons/ovh_telephony_connector/__init__.py
odoo_addons/ovh_telephony_connector/__openerp__.py
odoo_addons/ovh_telephony_connector/ovh_connector.py
odoo_addons/ovh_telephony_connector/res_users_view.xml
odoo_addons/ovh_telephony_connector/i18n/ar.po
odoo_addons/ovh_telephony_connector/i18n/ca.po
odoo_addons/ovh_telephony_connector/i18n/da.po
odoo_addons/ovh_telephony_connector/i18n/de.po
odoo_addons/ovh_telephony_connector/i18n/el_GR.po
odoo_addons/ovh_telephony_connector/i18n/es.po
odoo_addons/ovh_telephony_connector/i18n/es_ES.po
odoo_addons/ovh_telephony_connector/i18n/fi.po
odoo_addons/ovh_telephony_connector/i18n/fr.po
odoo_addons/ovh_telephony_connector/i18n/fr_CH.po
odoo_addons/ovh_telephony_connector/i18n/hr.po
odoo_addons/ovh_telephony_connector/i18n/hr_HR.po
odoo_addons/ovh_telephony_connector/i18n/it.po
odoo_addons/ovh_telephony_connector/i18n/nl.po
odoo_addons/ovh_telephony_connector/i18n/ovh_telephony_connector.pot
odoo_addons/ovh_telephony_connector/i18n/pt_BR.po
odoo_addons/ovh_telephony_connector/i18n/sl.po
odoo_addons/ovh_telephony_connector/i18n/tr.po
odoo_addons/ovh_telephony_connector/i18n/tr_TR.po
odoo_addons/ovh_telephony_connector/i18n/zh_CN.po
odoo_addons/ovh_telephony_connector/static/description/icon.png
odoo_addons/ovh_telephony_connector/static/src/xml/ovh_connector.xml
