Metadata-Version: 2.1
Name: odoo8-addon-ovh-telephony-connector
Version: 8.0.0.1.0.99.dev10
Summary: OVH-Odoo telephony connector (click2call)
Home-page: http://www.akretion.com/
Author: Akretion
Author-email: UNKNOWN
License: AGPL-3
Platform: UNKNOWN
Classifier: Programming Language :: Python
Classifier: Framework :: Odoo
Classifier: License :: OSI Approved :: GNU Affero General Public License v3
Requires-Python: ~=2.7
Requires-Dist: SOAPpy
Requires-Dist: odoo8-addon-base-phone
Requires-Dist: odoo (<9.0a,>=8.0a)
Requires-Dist: phonenumbers
